trailing/MultiAssetNewTradingBot.py
trailing/MultiAssetOldTradingBot.py
trailing/ThreeLineTradingBot.py
trailing/__init__.py
trailing/chua_bitget.py
trailing/chua_bn.py
trailing/chua_ok.py
trailing/chua_ok_all.py
trailing/chua_ok_bot.py
trailing/config.py
trailing/main.py
trailing/okx/Account_api.py
trailing/okx/Affiliate_api.py
trailing/okx/Broker_api.py
trailing/okx/Convert_api.py
trailing/okx/Copytrading_api.py
trailing/okx/FDBroker_api.py
trailing/okx/Finance_api.py
trailing/okx/Funding_api.py
trailing/okx/Market_api.py
trailing/okx/Public_api.py
trailing/okx/Recurring_api.py
trailing/okx/Rfq_api.py
trailing/okx/SprdApi_api.py
trailing/okx/Trade_api.py
trailing/okx/TradingBot_api.py
trailing/okx/TradingData_api.py
trailing/okx/__init__.py
trailing/okx/client.py
trailing/okx/consts.py
trailing/okx/exceptions.py
trailing/okx/status_api.py
trailing/okx/subAccount_api.py
trailing/okx/utils.py
openfund_trailing-1.3.0.dist-info/METADATA
openfund_trailing-1.3.0.dist-info/WHEEL
openfund_trailing-1.3.0.dist-info/entry_points.txt
openfund_trailing-1.3.0.dist-info/RECORD
